uscovid.py
uscovid-0.0.12.dist-info/METADATA
uscovid-0.0.12.dist-info/WHEEL
uscovid-0.0.12.dist-info/entry_points.txt
uscovid-0.0.12.dist-info/top_level.txt
uscovid-0.0.12.dist-info/RECORD
